ScenarioGUI/__init__.py
ScenarioGUI/global_settings.py
ScenarioGUI/translation_csv_to_py.py
ScenarioGUI/gui_classes/__init__.py
ScenarioGUI/gui_classes/gui_base_class.py
ScenarioGUI/gui_classes/gui_calculation_thread.py
ScenarioGUI/gui_classes/gui_combine_window.py
ScenarioGUI/gui_classes/gui_data_storage.py
ScenarioGUI/gui_classes/gui_saving_thread.py
ScenarioGUI/gui_classes/gui_structure.py
ScenarioGUI/gui_classes/status_bar_logger.py
ScenarioGUI/gui_classes/translation_class.py
ScenarioGUI/gui_classes/gui_structure_classes/__init__.py
ScenarioGUI/gui_classes/gui_structure_classes/aim.py
ScenarioGUI/gui_classes/gui_structure_classes/button_box.py
ScenarioGUI/gui_classes/gui_structure_classes/category.py
ScenarioGUI/gui_classes/gui_structure_classes/figure_option.py
ScenarioGUI/gui_classes/gui_structure_classes/filename_box.py
ScenarioGUI/gui_classes/gui_structure_classes/flexible_amount_option.py
ScenarioGUI/gui_classes/gui_structure_classes/float_box.py
ScenarioGUI/gui_classes/gui_structure_classes/float_box_with_units.py
ScenarioGUI/gui_classes/gui_structure_classes/font_list_box.py
ScenarioGUI/gui_classes/gui_structure_classes/function_button.py
ScenarioGUI/gui_classes/gui_structure_classes/functions.py
ScenarioGUI/gui_classes/gui_structure_classes/hint.py
ScenarioGUI/gui_classes/gui_structure_classes/int_box.py
ScenarioGUI/gui_classes/gui_structure_classes/int_box_with_units.py
ScenarioGUI/gui_classes/gui_structure_classes/list_box.py
ScenarioGUI/gui_classes/gui_structure_classes/matrix_option.py
ScenarioGUI/gui_classes/gui_structure_classes/multiple_int_box.py
ScenarioGUI/gui_classes/gui_structure_classes/option.py
ScenarioGUI/gui_classes/gui_structure_classes/page.py
ScenarioGUI/gui_classes/gui_structure_classes/result_export.py
ScenarioGUI/gui_classes/gui_structure_classes/result_figure.py
ScenarioGUI/gui_classes/gui_structure_classes/result_text.py
ScenarioGUI/gui_classes/gui_structure_classes/subcategory.py
ScenarioGUI-0.3.1.dist-info/LICENSE
ScenarioGUI-0.3.1.dist-info/METADATA
ScenarioGUI-0.3.1.dist-info/WHEEL
ScenarioGUI-0.3.1.dist-info/top_level.txt
ScenarioGUI-0.3.1.dist-info/RECORD
