Metadata-Version: 2.1
Name: ScenarioGUI
Version: 0.3.1
Summary: Python package for a scenario based GUI
Home-page: https://github.com/tblanke/ScenarioGUI
Author: Tobias Blanke
Author-email: blanke@fh-aachen.de
Classifier: Programming Language :: Python :: 3
Classifier: Programming Language :: Python :: 3.8
Classifier: Programming Language :: Python :: 3.9
Classifier: Programming Language :: Python :: 3.10
Classifier: Programming Language :: Python :: 3.11
Classifier: License :: OSI Approved :: BSD License
Classifier: Operating System :: OS Independent
Requires-Python: >=3.8
License-File: LICENSE
Requires-Dist: matplotlib >=3.5.2
Requires-Dist: numpy >=1.23.1
Requires-Dist: PySide6 >=6.4.1
Provides-Extra: gui
Requires-Dist: pyside6 >=6.4.1 ; extra == 'gui'
